{"Title":"Devil's Island","Year":"2021","Rated":"N/A","Released":"15 Mar 2021","Runtime":"71 min","Genre":"Horror, Thriller","Director":"Sean King, Taylor King","Writer":"Sean King, Taylor King","Actors":"Elaine Alexander, Kristjan Sokoli, Pete Berwick","Plot":"A young woman inherits a small island in New York and discovers it has a dangerous history.","Language":"English","Country":"United States","Awards":"N/A","Poster":"https://m.media-amazon.com/images/M/MV5BMTNjMTU2MzEtY2JkNy00ODhjLWIwMGItOWEwNDcwZTNmNzFkXkEyXkFqcGdeQXVyNjQ1MTEyNTE@._V1_SX300.jpg","Ratings":[{"Source":"Internet Movie Database","Value":"3.6/10"}],"Metascore":"N/A","imdbRating":"3.6","imdbVotes":"964","imdbID":"tt12496582","Type":"movie","DVD":"N/A","BoxOffice":"N/A","Production":"N/A","Website":"N/A","Response":"True"}