{"Title":"Sole Survivor","Year":"1984","Rated":"R","Released":"27 Jan 1984","Runtime":"85 min","Genre":"Horror, Thriller","Director":"Thom Eberhardt","Writer":"Thom Eberhardt","Actors":"Anita Skinner, Caren L. Larkey, Peggy McClure","Plot":"A lone survivor of a plane crash is haunted by a feeling unworthy of survival. Dead people start coming after her to collect her.","Language":"English","Country":"United States","Awards":"N/A","Poster":"https://m.media-amazon.com/images/M/MV5BMzJkNmRhMzMtOTUyZS00OGI5LWI3YTUtNmM4MjRhYTY3OWRmXkEyXkFqcGdeQXVyMTQxNzMzNDI@._V1_SX300.jpg","Ratings":[{"Source":"Internet Movie Database","Value":"6.1/10"}],"Metascore":"N/A","imdbRating":"6.1","imdbVotes":"2,326","imdbID":"tt0181012","Type":"movie","DVD":"N/A","BoxOffice":"N/A","Production":"N/A","Website":"N/A","Response":"True"}