{"Title":"The Final Terror","Year":"1983","Rated":"R","Released":"14 Jul 1983","Runtime":"84 min","Genre":"Horror","Director":"Andrew Davis","Writer":"Jon George, Neill D. Hicks, Ronald Shusett","Actors":"John Friedrich, Adrian Zmed, Ernest Harden Jr.","Plot":"A group of rangers go camping on unfamiliar forest grounds. All's well until the group members start getting killed by a cunning killer in the woods.","Language":"English","Country":"United States","Awards":"N/A","Poster":"https://m.media-amazon.com/images/M/MV5BMzQwZDAwYjctNmM2Mi00ZTljLWEwNzAtNWYxNTRhNzNkNTBhXkEyXkFqcGdeQXVyMTQxNzMzNDI@._V1_SX300.jpg","Ratings":[{"Source":"Internet Movie Database","Value":"5.2/10"},{"Source":"Rotten Tomatoes","Value":"33%"}],"Metascore":"N/A","imdbRating":"5.2","imdbVotes":"3,527","imdbID":"tt0082379","Type":"movie","DVD":"08 Jan 2017","BoxOffice":"N/A","Production":"N/A","Website":"N/A","Response":"True"}