{"Title":"The Amityville Horror","Year":"2005","Rated":"R","Released":"15 Apr 2005","Runtime":"90 min","Genre":"Horror","Director":"Andrew Douglas","Writer":"Scott Kosar, Jay Anson, Sandor Stern","Actors":"Ryan Reynolds, Melissa George, Jimmy Bennett","Plot":"Newlyweds are terrorized by demonic forces after moving into a large house that was the site of a grisly mass murder a year before.","Language":"English","Country":"United States","Awards":"2 wins & 4 nominations","Poster":"https://m.media-amazon.com/images/M/MV5BNzhlMzJkNzgtNDljNS00ZWY1LTg2ZjMtMTUxM2ExNWFlZTAyXkEyXkFqcGdeQXVyNjc3MjQzNTI@._V1_SX300.jpg","Ratings":[{"Source":"Internet Movie Database","Value":"5.9/10"},{"Source":"Rotten Tomatoes","Value":"24%"},{"Source":"Metacritic","Value":"33/100"}],"Metascore":"33","imdbRating":"5.9","imdbVotes":"115,852","imdbID":"tt0384806","Type":"movie","DVD":"01 Mar 2017","BoxOffice":"$65,233,369","Production":"N/A","Website":"N/A","Response":"True"}